iconetto/__init__.py
iconetto/__main__.py
iconetto/iconetto.py
iconetto/media/bg-image.png
iconetto/noodles/__init__.py
iconetto/noodles/converter.py
iconetto/noodles/create_color_preview.py
iconetto/noodles/overlay_image.py
iconetto/noodles/update_factory.py
iconetto/noodles/word_salad.py
iconetto-0.1.0.dist-info/licenses/LICENSE
iconetto-0.1.0.dist-info/METADATA
iconetto-0.1.0.dist-info/WHEEL
iconetto-0.1.0.dist-info/entry_points.txt
iconetto-0.1.0.dist-info/top_level.txt
iconetto-0.1.0.dist-info/RECORD
