Metadata-Version: 2.4
Name: iconetto
Version: 0.1.0
Summary: iconetto is a demo app showcasing the capabilities of iconipy, a package for generating clean, scalable, and customizable icons via code
Author-email: Björn Seipel <support@digidigital.de>
License-Expression: MIT
Project-URL: Homepage, https://digidigital.de
Project-URL: Repository, https://github.com/digidigital/iconetto
Project-URL: Support, https://github.com/digidigital/iconetto/issues
Keywords: icons,iconipy,ui,gui,user-interface
Classifier: Development Status :: 3 - Alpha
Classifier: Intended Audience :: End Users/Desktop
Classifier: Programming Language :: Python :: 3.9
Classifier: Programming Language :: Python :: 3.10
Classifier: Programming Language :: Python :: 3.11
Classifier: Programming Language :: Python :: 3.12
Classifier: Operating System :: OS Independent
Requires-Python: >=3.9
License-File: LICENSE
Requires-Dist: iconipy
Requires-Dist: pillow
Requires-Dist: FreeSimpleGUI
Dynamic: license-file
